[
  {
    "page": 2,
    "bbox": [
      247.1829833984375,
      155.37890625,
      313.2335510253906,
      174.2779541015625
    ],
    "caption": "N",
    "file_name": [
      "figures/fileoutpart0.png"
    ],
    "output_file": "assets/images/paper/Deep-Multimodal-Guidance-for-Medical-Image-Classification/fig_01.png"
  },
  {
    "page": 2,
    "bbox": [
      281.11500549316406,
      161.70555114746094,
      286.38719177246094,
      169.7114715576172
    ],
    "caption": "N",
    "file_name": ""
  },
  {
    "page": 2,
    "bbox": [
      297.2209930419922,
      161.70555114746094,
      302.1165771484375,
      168.67935180664062
    ],
    "caption": "",
    "file_name": ""
  },
  {
    "page": 2,
    "bbox": [
      247.1829833984375,
      155.37890625,
      313.2335510253906,
      174.2779541015625
    ],
    "caption": "N",
    "file_name": ""
  },
  {
    "page": 2,
    "bbox": [
      335.6394348144531,
      155.37890625,
      396.37095642089844,
      174.82046508789062
    ],
    "caption": "i",
    "file_name": [
      "figures/fileoutpart1.png"
    ],
    "output_file": "assets/images/paper/Deep-Multimodal-Guidance-for-Medical-Image-Classification/fig_05.png"
  },
  {
    "page": 2,
    "bbox": [
      342.7489929199219,
      161.70555114746094,
      348.0211944580078,
      169.7114715576172
    ],
    "caption": "i",
    "file_name": ""
  },
  {
    "page": 2,
    "bbox": [
      381.718994140625,
      166.81454467773438,
      388.0302734375,
      173.78834533691406
    ],
    "caption": "is the set of paired inferior and superior images, i.e. (x i I, x i S) is the ith pair. The set of training labels is Y = {y}, where y∈ L and L = {l, l, ..., l} is",
    "file_name": ""
  },
  {
    "page": 2,
    "bbox": [
      381.718994140625,
      160.6078643798828,
      384.5364685058594,
      167.5816650390625
    ],
    "caption": "",
    "file_name": ""
  },
  {
    "page": 2,
    "bbox": [
      384.5364227294922,
      160.6078643798828,
      396.37095642089844,
      168.61378479003906
    ],
    "caption": "",
    "file_name": ""
  },
  {
    "page": 2,
    "bbox": [
      335.6394348144531,
      155.37890625,
      396.37095642089844,
      174.82046508789062
    ],
    "caption": "i",
    "file_name": ""
  },
  {
    "page": 2,
    "bbox": [
      416.7003936767578,
      155.37890625,
      483.0852508544922,
      174.82046508789062
    ],
    "caption": "K",
    "file_name": [
      "figures/fileoutpart2.png"
    ],
    "output_file": "assets/images/paper/Deep-Multimodal-Guidance-for-Medical-Image-Classification/fig_11.png"
  },
  {
    "page": 2,
    "bbox": [
      423.81199645996094,
      161.70555114746094,
      430.45106506347656,
      169.7114715576172
    ],
    "caption": "1",
    "file_name": ""
  },
  {
    "page": 2,
    "bbox": [
      453.54200744628906,
      166.81454467773438,
      458.1028594970703,
      174.82046508789062
    ],
    "caption": "is the set of paired inferior and superior images, i.e. (x i I, x i S) is the ith pair. The set of training labels is Y = {y}, where y∈ L and L = {l, l, ..., l} is",
    "file_name": ""
  },
  {
    "page": 2,
    "bbox": [
      464.42100524902344,
      166.81454467773438,
      470.73228454589844,
      173.78834533691406
    ],
    "caption": "is the set of paired inferior and superior images, i.e. (x i I, x i S) is the ith pair. The set of training labels is Y = {y}, where y∈ L and L = {l, l, ..., l} is",
    "file_name": ""
  },
  {
    "page": 2,
    "bbox": [
      464.42100524902344,
      160.6078643798828,
      467.23846435546875,
      167.5816650390625
    ],
    "caption": "K",
    "file_name": ""
  },
  {
    "page": 2,
    "bbox": [
      467.23841857910156,
      160.6078643798828,
      477.3295440673828,
      167.5816650390625
    ],
    "caption": "",
    "file_name": ""
  },
  {
    "page": 2,
    "bbox": [
      416.7003936767578,
      155.37890625,
      483.0852508544922,
      174.82046508789062
    ],
    "caption": "K",
    "file_name": ""
  },
  {
    "page": 2,
    "bbox": [
      134.75286865234375,
      131.46878051757812,
      483.0828094482422,
      162.865478515625
    ],
    "caption": "N",
    "file_name": [
      "figures/fileoutpart3.png"
    ],
    "output_file": "assets/images/paper/Deep-Multimodal-Guidance-for-Medical-Image-Classification/fig_18.png"
  },
  {
    "page": 2,
    "bbox": [
      275.80999755859375,
      137.7945556640625,
      278.62745666503906,
      144.7683563232422
    ],
    "caption": "X = {X, X},",
    "file_name": ""
  },
  {
    "page": 2,
    "bbox": [
      284.1080017089844,
      142.90455627441406,
      290.4192810058594,
      149.87835693359375
    ],
    "caption": "X = {X, X},",
    "file_name": ""
  },
  {
    "page": 2,
    "bbox": [
      284.1080017089844,
      136.69786071777344,
      297.01654052734375,
      143.67166137695312
    ],
    "caption": "X = {X, X},",
    "file_name": ""
  },
  {
    "page": 2,
    "bbox": [
      339.1699981689453,
      137.7945556640625,
      343.7308654785156,
      145.80047607421875
    ],
    "caption": "X= {x }i I",
    "file_name": ""
  },
  {
    "page": 2,
    "bbox": [
      420.5010070800781,
      137.7945556640625,
      424.4761199951172,
      144.7683563232422
    ],
    "caption": "X= {x}S,",
    "file_name": ""
  },
  {
    "page": 2,
    "bbox": [
      432.3710021972656,
      137.7945556640625,
      436.3461151123047,
      144.7683563232422
    ],
    "caption": "X= {x}S,",
    "file_name": ""
  },
  {
    "page": 2,
    "bbox": [
      456.9709930419922,
      137.7945556640625,
      465.4093017578125,
      145.80047607421875
    ],
    "caption": "X= {x}S,",
    "file_name": ""
  },
  {
    "page": 2,
    "bbox": [
      134.75286865234375,
      131.46878051757812,
      483.0828094482422,
      162.865478515625
    ],
    "caption": "N",
    "file_name": ""
  },
  {
    "page": 3,
    "bbox": [
      134.764892578125,
      569.0426177978516,
      477.55633544921875,
      676.1651153564453
    ],
    "caption": "Fig. 1: Overview of the multimodal guidance approach. (a) Two independent modality-specific (inferior I vs superior S) classifiers are trained, each with encoder E—producing latent representation z—and decoder D. (b) The architecture of the guidance model G. (c) G connects the output of the (frozen) inferior modality encoder EI to the input of the (frozen) superior modality decoder DS . Then G is trained to infer the latent representation of the superior modality from the inferior one. (d) The final model, whose input is the inferior modality alone, uses both the inferior and the estimated superior modality representations to make the final prediction via the trained combined decoder Dc.",
    "file_name": [
      "figures/fileoutpart4.png"
    ],
    "output_file": "assets/images/paper/Deep-Multimodal-Guidance-for-Medical-Image-Classification/fig_27.png"
  },
  {
    "page": 3,
    "bbox": [
      134.764892578125,
      569.0426177978516,
      477.55633544921875,
      676.1651153564453
    ],
    "caption": "Fig. 1: Overview of the multimodal guidance approach. (a) Two independent modality-specific (inferior I vs superior S) classifiers are trained, each with encoder E—producing latent representation z—and decoder D. (b) The architecture of the guidance model G. (c) G connects the output of the (frozen) inferior modality encoder EI to the input of the (frozen) superior modality decoder DS . Then G is trained to infer the latent representation of the superior modality from the inferior one. (d) The final model, whose input is the inferior modality alone, uses both the inferior and the estimated superior modality representations to make the final prediction via the trained combined decoder Dc.",
    "file_name": ""
  },
  {
    "page": 3,
    "bbox": [
      366.39207458496094,
      220.91343688964844,
      382.43345642089844,
      240.1686553955078
    ],
    "caption": "ˆy i I = CI(x i I ) ˆy i S = CS (x i S ),",
    "file_name": [
      "figures/fileoutpart5.png"
    ],
    "output_file": "assets/images/paper/Deep-Multimodal-Guidance-for-Medical-Image-Classification/fig_29.png"
  },
  {
    "page": 3,
    "bbox": [
      371.27732849121094,
      220.91343688964844,
      377.9165802001953,
      233.80836486816406
    ],
    "caption": "ˆy i I = CI(x i I ) ˆy i S = CS (x i S ),",
    "file_name": ""
  },
  {
    "page": 3,
    "bbox": [
      366.39207458496094,
      220.91343688964844,
      382.43345642089844,
      240.1686553955078
    ],
    "caption": "ˆy i I = CI(x i I ) ˆy i S = CS (x i S ),",
    "file_name": ""
  },
  {
    "page": 3,
    "bbox": [
      240.5603485107422,
      190.68524169921875,
      377.28306579589844,
      210.15664672851562
    ],
    "caption": "where CI , and similarly CS , comprise an encoder E, which encodes the high-dimensional input image into a compact low-dimensional latent representation, and a decoder D, which decodes the latent representation by mapping it to one of the labels in L. Denoting the encoder and decoder in CI as EI and DI , respectively, and similarly ES and DS in CS , we obtain:",
    "file_name": [
      "figures/fileoutpart6.png"
    ],
    "output_file": "assets/images/paper/Deep-Multimodal-Guidance-for-Medical-Image-Classification/fig_32.png"
  },
  {
    "page": 3,
    "bbox": [
      240.5603485107422,
      190.68524169921875,
      377.28306579589844,
      210.15664672851562
    ],
    "caption": "where CI , and similarly CS , comprise an encoder E, which encodes the high-dimensional input image into a compact low-dimensional latent representation, and a decoder D, which decodes the latent representation by mapping it to one of the labels in L. Denoting the encoder and decoder in CI as EI and DI , respectively, and similarly ES and DS in CS , we obtain:",
    "file_name": ""
  },
  {
    "page": 4,
    "bbox": [
      196.5415802001953,
      644.6829071044922,
      421.30470275878906,
      664.6224670410156
    ],
    "caption": "z i I = EI (x i I ; θEI ) z i S = ES (x i S ; θES ).",
    "file_name": [
      "figures/fileoutpart7.png"
    ],
    "output_file": "assets/images/paper/Deep-Multimodal-Guidance-for-Medical-Image-Classification/fig_34.png"
  },
  {
    "page": 4,
    "bbox": [
      196.5415802001953,
      644.6829071044922,
      421.30470275878906,
      664.6224670410156
    ],
    "caption": "z i I = EI (x i I ; θEI ) z i S = ES (x i S ; θES ).",
    "file_name": ""
  },
  {
    "page": 4,
    "bbox": [
      220.128173828125,
      592.1776275634766,
      397.7176971435547,
      611.6484680175781
    ],
    "caption": "Guidance Model G (Figure (b-c)): G is trained to map zIi of the inferior image to zSi of the paired superior image. Denoting the estimated latent code as zˆSi and the parameters of G as θG, we obtain:",
    "file_name": [
      "figures/fileoutpart8.png"
    ],
    "output_file": "assets/images/paper/Deep-Multimodal-Guidance-for-Medical-Image-Classification/fig_36.png"
  },
  {
    "page": 4,
    "bbox": [
      220.128173828125,
      592.1776275634766,
      397.7176971435547,
      611.6484680175781
    ],
    "caption": "Guidance Model G (Figure (b-c)): G is trained to map zIi of the inferior image to zSi of the paired superior image. Denoting the estimated latent code as zˆSi and the parameters of G as θG, we obtain:",
    "file_name": ""
  },
  {
    "page": 4,
    "bbox": [
      273.64540100097656,
      481.0416259765625,
      344.20269775390625,
      500.51246643066406
    ],
    "caption": "Guided Model F (Figure (d)): We incorporate the trained guidance model G into the classification model of the inferior modality CI so that it is steered to inherit the knowledge captured by the classifier CS , which was trained on the superior modality but without CI being exposed to the superior image modality. The model F is thus able, during inference time, to make a prediction based solely on the inferior modality while being steered to generate internal representations that mimic those produced by models trained on superior data. The superior modality encoder can thus be viewed as a teacher distilling its knowledge (the learned latent representation) to benefit the inferior modality student classifier. At inference time, we need not rely only on the guided representations zˆSi to make predictions, but rather benefit from the learned representations zI from the inferior modality as well. Therefore, the two concatenated representations are used to train a common classification decoder with parameters θDc , where  is the concatenation operator. Thus, our final prediction yˆ = F (xI ; θ) is written as follows, with θ = {θEI , θG, θDc }:",
    "file_name": [
      "figures/fileoutpart9.png"
    ],
    "output_file": "assets/images/paper/Deep-Multimodal-Guidance-for-Medical-Image-Classification/fig_38.png"
  },
  {
    "page": 4,
    "bbox": [
      273.64540100097656,
      481.0416259765625,
      344.20269775390625,
      500.51246643066406
    ],
    "caption": "Guided Model F (Figure (d)): We incorporate the trained guidance model G into the classification model of the inferior modality CI so that it is steered to inherit the knowledge captured by the classifier CS , which was trained on the superior modality but without CI being exposed to the superior image modality. The model F is thus able, during inference time, to make a prediction based solely on the inferior modality while being steered to generate internal representations that mimic those produced by models trained on superior data. The superior modality encoder can thus be viewed as a teacher distilling its knowledge (the learned latent representation) to benefit the inferior modality student classifier. At inference time, we need not rely only on the guided representations zˆSi to make predictions, but rather benefit from the learned representations zI from the inferior modality as well. Therefore, the two concatenated representations are used to train a common classification decoder with parameters θDc , where  is the concatenation operator. Thus, our final prediction yˆ = F (xI ; θ) is written as follows, with θ = {θEI , θG, θDc }:",
    "file_name": ""
  },
  {
    "page": 4,
    "bbox": [
      330.8830871582031,
      316.7548065185547,
      410.6427001953125,
      336.0094757080078
    ],
    "caption": "ˆy = Dc  [G  EI (x i I ; θEI ); θG  EI  x i I ; θEI  ]; θDc  .",
    "file_name": [
      "figures/fileoutpart10.png"
    ],
    "output_file": "assets/images/paper/Deep-Multimodal-Guidance-for-Medical-Image-Classification/fig_40.png"
  },
  {
    "page": 4,
    "bbox": [
      339.1260070800781,
      322.8935546875,
      342.6896209716797,
      329.8673553466797
    ],
    "caption": "ˆy = Dc  [G  EI (x i I ; θEI ); θG  EI  x i I ; θEI  ]; θDc  .",
    "file_name": ""
  },
  {
    "page": 4,
    "bbox": [
      354.8970031738281,
      328.00355529785156,
      359.45787048339844,
      336.0094757080078
    ],
    "caption": "ˆy = Dc  [G  EI (x i I ; θEI ); θG  EI  x i I ; θEI  ]; θDc  .",
    "file_name": ""
  },
  {
    "page": 4,
    "bbox": [
      354.45765686035156,
      316.7548065185547,
      359.3532257080078,
      328.8404083251953
    ],
    "caption": "ˆy = Dc  [G  EI (x i I ; θEI ); θG  EI  x i I ; θEI  ]; θDc  .",
    "file_name": ""
  },
  {
    "page": 4,
    "bbox": [
      360.35748291015625,
      328.00355529785156,
      368.3006896972656,
      334.97735595703125
    ],
    "caption": "ˆy = Dc  [G  EI (x i I ; θEI ); θG  EI  x i I ; θEI  ]; θDc  .",
    "file_name": ""
  },
  {
    "page": 4,
    "bbox": [
      373.86900329589844,
      328.00355529785156,
      378.42987060546875,
      336.0094757080078
    ],
    "caption": "ˆy = Dc  [G  EI (x i I ; θEI ); θG  EI  x i I ; θEI  ]; θDc  .",
    "file_name": ""
  },
  {
    "page": 4,
    "bbox": [
      373.4296569824219,
      316.7548065185547,
      377.9417266845703,
      328.8404083251953
    ],
    "caption": "ˆy = Dc  [G  EI (x i I ; θEI ); θG  EI  x i I ; θEI  ]; θDc  .",
    "file_name": ""
  },
  {
    "page": 4,
    "bbox": [
      390.7619934082031,
      322.3956756591797,
      401.7541961669922,
      329.8673553466797
    ],
    "caption": "ˆy = Dc  [G  EI (x i I ; θEI ); θG  EI  x i I ; θEI  ]; θDc  .",
    "file_name": ""
  },
  {
    "page": 4,
    "bbox": [
      330.8830871582031,
      316.7548065185547,
      410.6427001953125,
      336.0094757080078
    ],
    "caption": "ˆy = Dc  [G  EI (x i I ; θEI ); θG  EI  x i I ; θEI  ]; θDc  .",
    "file_name": ""
  },
  {
    "page": 4,
    "bbox": [
      196.1567840576172,
      256.8907012939453,
      421.6858825683594,
      295.326416015625
    ],
    "caption": "Datasets: We evaluate our method on two multimodal imaging applications:",
    "file_name": [
      "figures/fileoutpart11.png"
    ],
    "output_file": "assets/images/paper/Deep-Multimodal-Guidance-for-Medical-Image-Classification/fig_49.png"
  },
  {
    "page": 4,
    "bbox": [
      196.1567840576172,
      256.8907012939453,
      421.6858825683594,
      295.326416015625
    ],
    "caption": "Datasets: We evaluate our method on two multimodal imaging applications:",
    "file_name": ""
  },
  {
    "page": 11,
    "bbox": [
      466.0316619873047,
      494.5949249267578,
      472.20623779296875,
      499.0194396972656
    ],
    "caption": "-",
    "file_name": [
      "figures/fileoutpart18.png"
    ],
    "output_file": "assets/images/paper/Deep-Multimodal-Guidance-for-Medical-Image-Classification/table_557.png"
  },
  {
    "page": 11,
    "bbox": [
      466.0316619873047,
      487.0796813964844,
      472.20623779296875,
      491.5041961669922
    ],
    "caption": "-",
    "file_name": [
      "figures/fileoutpart19.png"
    ],
    "output_file": "assets/images/paper/Deep-Multimodal-Guidance-for-Medical-Image-Classification/table_581.png"
  },
  {
    "page": 11,
    "bbox": [
      466.0316619873047,
      479.56443786621094,
      472.20623779296875,
      483.98895263671875
    ],
    "caption": "-",
    "file_name": [
      "figures/fileoutpart20.png"
    ],
    "output_file": "assets/images/paper/Deep-Multimodal-Guidance-for-Medical-Image-Classification/table_605.png"
  },
  {
    "page": 11,
    "bbox": [
      466.0316619873047,
      464.5346374511719,
      472.20623779296875,
      468.9591522216797
    ],
    "caption": "-",
    "file_name": [
      "figures/fileoutpart21.png"
    ],
    "output_file": "assets/images/paper/Deep-Multimodal-Guidance-for-Medical-Image-Classification/table_653.png"
  },
  {
    "page": 12,
    "bbox": [
      153.63099670410156,
      431.01499938964844,
      289.1925964355469,
      524.2135925292969
    ],
    "caption": "(a) % BA improvements in Derm7pt",
    "file_name": [
      "figures/fileoutpart24.png"
    ],
    "output_file": "assets/images/paper/Deep-Multimodal-Guidance-for-Medical-Image-Classification/fig_55.png"
  },
  {
    "page": 12,
    "bbox": [
      153.63099670410156,
      319.88299560546875,
      289.1925964355469,
      413.08160400390625
    ],
    "caption": "(c) % BA improvements in RadPath",
    "file_name": [
      "figures/fileoutpart25.png"
    ],
    "output_file": "assets/images/paper/Deep-Multimodal-Guidance-for-Medical-Image-Classification/fig_56.png"
  },
  {
    "page": 12,
    "bbox": [
      326.15899658203125,
      431.01499938964844,
      461.72059631347656,
      524.2135925292969
    ],
    "caption": "(b) % F1 improvements in Derm7pt",
    "file_name": [
      "figures/fileoutpart26.png"
    ],
    "output_file": "assets/images/paper/Deep-Multimodal-Guidance-for-Medical-Image-Classification/fig_57.png"
  },
  {
    "page": 12,
    "bbox": [
      326.15899658203125,
      319.88299560546875,
      461.72059631347656,
      413.08160400390625
    ],
    "caption": "(d) % F1 improvements in RadPath",
    "file_name": [
      "figures/fileoutpart27.png"
    ],
    "output_file": "assets/images/paper/Deep-Multimodal-Guidance-for-Medical-Image-Classification/fig_58.png"
  }
]